MANIFEST.in
setup.py
version.py
django_orm/__init__.py
django_orm/dispatch.py
django_orm/models.py
django_orm/signals.py
django_orm/utils.py
django_orm/cache/__init__.py
django_orm/cache/exceptions.py
django_orm/cache/invalidator.py
django_orm/cache/manager.py
django_orm/cache/query_deprecated.py
django_orm/cache/queryset.py
django_orm/cache/utils.py
django_orm/core/__init__.py
django_orm/core/manager.py
django_orm/core/queryset.py
django_orm/core/sql/__init__.py
django_orm/core/sql/base.py
django_orm/core/sql/expressions.py
django_orm/core/sql/functions.py
django_orm/core/sql/tree.py
django_orm/core/sql/utils.py
django_orm/gis/__init__.py
django_orm/gis/manager.py
django_orm/gis/queryset.py
django_orm/mysql/__init__.py
django_orm/mysql/manager.py
django_orm/mysql/queryset.py
django_orm/postgresql/__init__.py
django_orm/postgresql/expressions.py
django_orm/postgresql/functions.py
django_orm/postgresql/manager.py
django_orm/postgresql/queryset.py
django_orm/postgresql/composite/__init__.py
django_orm/postgresql/fields/__init__.py
django_orm/postgresql/fields/arrays.py
django_orm/postgresql/fields/bytea.py
django_orm/postgresql/fields/interval.py
django_orm/postgresql/fulltext/__init__.py
django_orm/postgresql/fulltext/fields.py
django_orm/postgresql/fulltext/manager.py
django_orm/postgresql/geometric/__init__.py
django_orm/postgresql/geometric/adapt.py
django_orm/postgresql/geometric/expressions.py
django_orm/postgresql/geometric/fields.py
django_orm/postgresql/geometric/functions.py
django_orm/postgresql/geometric/objects.py
django_orm/postgresql/hstore/__init__.py
django_orm/postgresql/hstore/expressions.py
django_orm/postgresql/hstore/fields.py
django_orm/postgresql/hstore/forms.py
django_orm/postgresql/hstore/functions.py
django_orm/postgresql/hstore/manager.py
django_orm/postgresql/hstore/query_utils.py
django_orm/postgresql/hstore/queryset.py
django_orm/postgresql/hstore/util.py
django_orm/postgresql/sql/__init__.py
django_orm/postgresql/sql/aggregates.py
django_orm_extensions.egg-info/PKG-INFO
django_orm_extensions.egg-info/SOURCES.txt
django_orm_extensions.egg-info/dependency_links.txt
django_orm_extensions.egg-info/not-zip-safe
django_orm_extensions.egg-info/requires.txt
django_orm_extensions.egg-info/top_level.txt