Metadata-Version: 1.1
Name: django-orm-extensions
Version: 3.0b3
Summary: Advanced improvement of django-orm with a lot of third-party plugins for use different parts of databases are
Home-page: https://github.com/niwibe/django-orm-extensions
Author: Andrei Antoukh
Author-email: niwi@niwi.be
License: BSD
Platform: OS Independent
Classifier: Development Status :: 4 - Beta
Classifier: Framework :: Django
Classifier: Intended Audience :: Developers
Classifier: License :: OSI Approved :: BSD License
Classifier: Operating System :: OS Independent
Classifier: Programming Language :: Python
Classifier: Topic :: Internet :: WWW/HTTP
